{
  "projectionOrdering": {
    "Values": [
      0
    ]
  },
  "queryMetadata": {
    "Select": [
      {
        "Restatement": "Nb_Achats",
        "Name": "Fait_ACHATS.Nb_Achats",
        "Type": 3,
        "Format": "0"
      }
    ]
  },
  "visualElements": [
    {
      "DataRoles": [
        {
          "Name": "Values",
          "Projection": 0,
          "isActive": false
        }
      ]
    }
  ],
  "selects": [
    {
      "displayName": "Nb_Achats",
      "format": "0",
      "queryName": "Fait_ACHATS.Nb_Achats",
      "roles": {
        "Values": true
      },
      "type": {
        "category": null,
        "underlyingType": 260
      },
      "expr": {
        "Measure": {
          "Expression": {
            "SourceRef": {
              "Entity": "Fait_ACHATS"
            }
          },
          "Property": "Nb_Achats"
        }
      }
    }
  ]
}